vinzy_datadiff/__init__.py
vinzy_datadiff/datadiff.py
vinzy_datadiff-0.1.0.dist-info/licenses/LICENSE
vinzy_datadiff-0.1.0.dist-info/METADATA
vinzy_datadiff-0.1.0.dist-info/WHEEL
vinzy_datadiff-0.1.0.dist-info/top_level.txt
vinzy_datadiff-0.1.0.dist-info/RECORD
